utilsforecast/__init__.py
utilsforecast/compat.py
utilsforecast/data.py
utilsforecast/evaluation.py
utilsforecast/feature_engineering.py
utilsforecast/grouped_array.py
utilsforecast/losses.py
utilsforecast/plotting.py
utilsforecast/preprocessing.py
utilsforecast/processing.py
utilsforecast/py.typed
utilsforecast/validation.py
utilsforecast-0.2.14.dist-info/licenses/LICENSE
utilsforecast-0.2.14.dist-info/METADATA
utilsforecast-0.2.14.dist-info/WHEEL
utilsforecast-0.2.14.dist-info/top_level.txt
utilsforecast-0.2.14.dist-info/RECORD
