Metadata-Version: 2.4
Name: utilsforecast
Version: 0.2.14
Summary: Forecasting utilities
Author-email: Nixtla <business@nixtla.io>
License: Apache Software License 2.0
Project-URL: Homepage, https://github.com/Nixtla/utilsforecast
Project-URL: Documentation, https://nixtlaverse.verse.io/utilsforecast
Project-URL: Repository, https://github.com/Nixtla/utilsforecast
Keywords: time-series,analysis,forecasting
Classifier: Development Status :: 3 - Alpha
Classifier: Intended Audience :: Developers
Classifier: Natural Language :: English
Classifier: License :: OSI Approved :: Apache Software License
Classifier: Programming Language :: Python :: 3.9
Classifier: Programming Language :: Python :: 3.10
Classifier: Programming Language :: Python :: 3.11
Classifier: Programming Language :: Python :: 3.12
Classifier: Programming Language :: Python :: 3.13
Requires-Python: >=3.9
License-File: LICENSE
Requires-Dist: numpy
Requires-Dist: packaging
Requires-Dist: pandas>=1.1.1
Provides-Extra: plotting
Requires-Dist: pandas[plot]; extra == "plotting"
Requires-Dist: plotly; extra == "plotting"
Requires-Dist: plotly-resampler; extra == "plotting"
Provides-Extra: polars
Requires-Dist: polars[numpy]<=1.31; extra == "polars"
Provides-Extra: dev
Requires-Dist: black; extra == "dev"
Requires-Dist: datasetsforecast==0.0.8; extra == "dev"
Requires-Dist: nbformat; extra == "dev"
Requires-Dist: numba>=0.58.0; extra == "dev"
Requires-Dist: pip; extra == "dev"
Requires-Dist: pre-commit; extra == "dev"
Requires-Dist: pyarrow; extra == "dev"
Requires-Dist: scipy; extra == "dev"
Requires-Dist: pandas[plot]; extra == "dev"
Requires-Dist: plotly; extra == "dev"
Requires-Dist: plotly-resampler; extra == "dev"
Requires-Dist: polars[numpy]; extra == "dev"
Requires-Dist: pytest; extra == "dev"
Requires-Dist: pytest-cov; extra == "dev"
Requires-Dist: fugue[dask,spark]>=0.8.1; extra == "dev"
Requires-Dist: dask<=2024.12.1; extra == "dev"
Dynamic: license-file
